STMGraph/STDGraph.py
STMGraph/STGraphV1.py
STMGraph/STMGraph.py
STMGraph/STMGraphV1.py
STMGraph/Train_STMGraph.py
STMGraph/Train_STMGraphV1.py
STMGraph/__init__.py
STMGraph/calculate_moran_I.py
STMGraph/model.py
STMGraph/modelV1.py
STMGraph/model_or.py
STMGraph/model_orV1.py
STMGraph/test_M.py
STMGraph/utils.py
STMGraph-1.0.1.dist-info/METADATA
STMGraph-1.0.1.dist-info/WHEEL
STMGraph-1.0.1.dist-info/top_level.txt
STMGraph-1.0.1.dist-info/RECORD
