Metadata-Version: 2.1
Name: STMGraph
Version: 1.0.1
Summary: A spatial-context-aware of spatial transcriptomes package
Author-email: Lixian Lin <llx_1910@163.com>
Project-URL: Homepage, https://github.com/binbin_coder/STMGraph
Project-URL: Bug Tracker, https://github.com/binbin_coder/STMGraph/issues
Classifier: Programming Language :: Python :: 3
Classifier: License :: OSI Approved :: MIT License
Classifier: Operating System :: OS Independent
Requires-Python: >=3.7
